chemtrain/__init__.py
chemtrain/typing.py
chemtrain/util.py
chemtrain/version.py
chemtrain/data/__init__.py
chemtrain/data/data_loaders.py
chemtrain/data/preprocessing.py
chemtrain/deploy/__init__.py
chemtrain/deploy/exporter.py
chemtrain/deploy/graphs.py
chemtrain/deploy/util.py
chemtrain/deploy/_protobuf/__init__.py
chemtrain/deploy/_protobuf/model_pb2.py
chemtrain/ensemble/__init__.py
chemtrain/ensemble/evaluation.py
chemtrain/ensemble/reweighting.py
chemtrain/ensemble/sampling.py
chemtrain/ensemble/templates.py
chemtrain/learn/__init__.py
chemtrain/learn/difftre.py
chemtrain/learn/force_matching.py
chemtrain/learn/max_likelihood.py
chemtrain/learn/probabilistic.py
chemtrain/learn/property_prediction.py
chemtrain/quantity/__init__.py
chemtrain/quantity/constants.py
chemtrain/quantity/observables.py
chemtrain/quantity/property_prediction.py
chemtrain/quantity/targets/__init__.py
chemtrain/quantity/targets/structure.py
chemtrain/quantity/targets/thermodynamics.py
chemtrain/quantity/targets/util.py
chemtrain/trainers/__init__.py
chemtrain/trainers/base.py
chemtrain/trainers/extensions.py
chemtrain/trainers/trainers.py
chemtrain-0.2.0.dist-info/licenses/LICENSE
chemtrain-0.2.0.dist-info/licenses/LICENSE_SHORT
jax_md_mod/__init__.py
jax_md_mod/custom_energy.py
jax_md_mod/custom_interpolate.py
jax_md_mod/custom_partition.py
jax_md_mod/custom_quantity.py
jax_md_mod/custom_simulate.py
jax_md_mod/custom_space.py
jax_md_mod/e3nn_mod.py
jax_md_mod/io.py
jax_md_mod/model/__init__.py
jax_md_mod/model/dimenet_basis_util.py
jax_md_mod/model/dropout.py
jax_md_mod/model/layers.py
jax_md_mod/model/neural_networks.py
jax_md_mod/model/prior.py
jax_md_mod/model/sparse_graph.py
chemtrain-0.2.0.dist-info/METADATA
chemtrain-0.2.0.dist-info/WHEEL
chemtrain-0.2.0.dist-info/top_level.txt
chemtrain-0.2.0.dist-info/RECORD
