Metadata-Version: 2.4
Name: chemtrain
Version: 0.2.0
Summary: Machine-learning deep molecular dynamics potentials.
Author-email: Stephan Thaler <stephan.thaler@tum.de>, Paul Fuchs <paul.fuchs@tum.de>
License: Apache-2.0
Project-URL: Documentation, https://chemtrain.readthedocs.io/en/latest/
Project-URL: Source, https://github.com/tummfm/chemtrain
Project-URL: Bug Tracker, https://github.com/tummfm/chemtrain/issues
Classifier: Programming Language :: Python :: 3
Classifier: Programming Language :: Python :: 3.10
Classifier: Programming Language :: Python :: 3.11
Classifier: License :: OSI Approved :: Apache Software License
Classifier: Operating System :: MacOS
Classifier: Operating System :: POSIX :: Linux
Classifier: Topic :: Scientific/Engineering
Classifier: Intended Audience :: Science/Research
Classifier: Intended Audience :: Developers
Requires-Python: >=3.10
License-File: LICENSE
License-File: LICENSE_SHORT
Requires-Dist: jax<=0.4.37
Requires-Dist: jaxlib<=0.4.37
Requires-Dist: scipy<1.13
Requires-Dist: jax-md
Requires-Dist: jax-sgmc
Requires-Dist: optax
Requires-Dist: dm-haiku
Requires-Dist: sympy
Requires-Dist: tree_math
Requires-Dist: cloudpickle
Requires-Dist: chex
Requires-Dist: blackjax==0.3.0
Requires-Dist: jaxopt
Requires-Dist: dm-tree
Requires-Dist: networkx
Requires-Dist: protobuf<=3.20
Provides-Extra: all
Requires-Dist: mdtraj; extra == "all"
Requires-Dist: matplotlib; extra == "all"
Requires-Dist: tomli; extra == "all"
Requires-Dist: tomli-w; extra == "all"
Requires-Dist: scikit-learn; extra == "all"
Provides-Extra: test
Requires-Dist: pylint; extra == "test"
Requires-Dist: pytest; extra == "test"
Requires-Dist: pytest-mock; extra == "test"
Provides-Extra: docs
Requires-Dist: sphinx>=3; extra == "docs"
Requires-Dist: sphinx-book-theme; extra == "docs"
Requires-Dist: sphinx-autodoc-typehints==1.11.1; extra == "docs"
Requires-Dist: myst-nb; extra == "docs"
Requires-Dist: matplotlib; extra == "docs"
Requires-Dist: sphinx-remove-toctrees; extra == "docs"
Requires-Dist: breathe; extra == "docs"
Requires-Dist: sphinxcontrib-mermaid; extra == "docs"
Provides-Extra: stable
Requires-Dist: jax==0.3.25; extra == "stable"
Requires-Dist: jaxlib==0.3.25; extra == "stable"
Requires-Dist: chex==0.1.5; extra == "stable"
Requires-Dist: orbax-checkpoint==0.1.1; extra == "stable"
Requires-Dist: orbax==0.1.1; extra == "stable"
Dynamic: license-file
